hierarpy/__init__.py
hierarpy/core.py
hierarpy-1.1.2.dist-info/LICENSE
hierarpy-1.1.2.dist-info/METADATA
hierarpy-1.1.2.dist-info/WHEEL
hierarpy-1.1.2.dist-info/top_level.txt
hierarpy-1.1.2.dist-info/RECORD
