Metadata-Version: 2.1
Name: hierarpy
Version: 1.1.2
Summary: A library for hierarchical configuration in Python.
Home-page: https://github.com/rodrigo-castellon/hierarpy
Author: Rodrigo Castellon
Author-email: rjcaste@stanford.edu
License: MIT
Platform: UNKNOWN
License-File: LICENSE
Requires-Dist: addict
Requires-Dist: PyYAML
